{
  "contatos": [
    {
      "id": 1,
      "nome": "pedro tavares",
      "telefone": "9999-8888",
      "data": "2019-08-20T23:28:56.782Z",
      "operadora": {
        "nome": "Oi",
        "codigo": 14,
        "categoria": "Celular",
        "preco": 1
      }
    },
    {
      "id": 2,
      "nome": "ana maria braga",
      "telefone": "9999-8877",
      "data": "2019-08-20T23:28:56.782Z",
      "operadora": {
        "nome": "Vivo",
        "codigo": 15,
        "categoria": "Celular",
        "preco": 2
      }
    },
    {
      "id": 3,
      "nome": "maria alice de souza",
      "telefone": "9999-8866",
      "data": "2019-08-20T23:28:56.782Z",
      "operadora": {
        "nome": "Tim",
        "codigo": 41,
        "categoria": "Celular",
        "preco": 3
      }
    },
    {
      "nome": "hugo borges",
      "telefone": "2134-4455",
      "operadora": {
        "id": 1,
        "nome": "Oi",
        "codigo": 14,
        "categoria": "Celular",
        "preco": 2
      },
      "data": "2019-08-21T19:48:58.821Z",
      "id": 4
    }
  ],
  "operadora": [
    {
      "id": 1,
      "nome": "Oi",
      "codigo": 14,
      "categoria": "Celular",
      "preco": 2
    },
    {
      "id": 2,
      "nome": "Vivo",
      "codigo": 15,
      "categoria": "Celular",
      "preco": 1
    },
    {
      "id": 3,
      "nome": "Tim",
      "codigo": 41,
      "categoria": "Celular",
      "preco": 3
    },
    {
      "id": 4,
      "nome": "GVT",
      "codigo": 251,
      "categoria": "Fixo",
      "preco": 1
    },
    {
      "id": 5,
      "nome": "Embratel",
      "codigo": 21,
      "categoria": "Fixo",
      "preco": 2
    }
  ]
}
